<?xml version="1.0" encoding="utf-8"?>
<optionset Name="mda_plaidlanguages" localizedName="PlaidLanguages" xmlns:xsi="http://www.w3.org/2001/XMLSchema-instance">
  <OptionSetType>picklist</OptionSetType>
  <IsGlobal>1</IsGlobal>
  <IntroducedVersion>1.4.20260114.0</IntroducedVersion>
  <IsCustomizable>1</IsCustomizable>
  <ExternalTypeName></ExternalTypeName>
  <displaynames>
    <displayname description="PlaidLanguages" languagecode="1033" />
  </displaynames>
  <Descriptions>
    <Description description="" languagecode="1033" />
  </Descriptions>
  <options>
    <option value="0" ExternalValue="" IsHidden="0">
      <labels>
        <label description="DA" languagecode="1033" />
      </labels>
      <Descriptions>
        <Description description="" languagecode="1033" />
      </Descriptions>
    </option>
    <option value="1" ExternalValue="" IsHidden="0">
      <labels>
        <label description="NL" languagecode="1033" />
      </labels>
      <Descriptions>
        <Description description="" languagecode="1033" />
      </Descriptions>
    </option>
    <option value="2" ExternalValue="" IsHidden="0">
      <labels>
        <label description="EN" languagecode="1033" />
      </labels>
      <Descriptions>
        <Description description="" languagecode="1033" />
      </Descriptions>
    </option>
    <option value="3" ExternalValue="" IsHidden="0">
      <labels>
        <label description="ET" languagecode="1033" />
      </labels>
      <Descriptions>
        <Description description="" languagecode="1033" />
      </Descriptions>
    </option>
    <option value="4" ExternalValue="" IsHidden="0">
      <labels>
        <label description="FR" languagecode="1033" />
      </labels>
      <Descriptions>
        <Description description="" languagecode="1033" />
      </Descriptions>
    </option>
    <option value="5" ExternalValue="" IsHidden="0">
      <labels>
        <label description="DE" languagecode="1033" />
      </labels>
      <Descriptions>
        <Description description="" languagecode="1033" />
      </Descriptions>
    </option>
    <option value="6" ExternalValue="" IsHidden="0">
      <labels>
        <label description="HI" languagecode="1033" />
      </labels>
      <Descriptions>
        <Description description="" languagecode="1033" />
      </Descriptions>
    </option>
    <option value="7" ExternalValue="" IsHidden="0">
      <labels>
        <label description="IT" languagecode="1033" />
      </labels>
      <Descriptions>
        <Description description="" languagecode="1033" />
      </Descriptions>
    </option>
    <option value="8" ExternalValue="" IsHidden="0">
      <labels>
        <label description="LV" languagecode="1033" />
      </labels>
      <Descriptions>
        <Description description="" languagecode="1033" />
      </Descriptions>
    </option>
    <option value="9" ExternalValue="" IsHidden="0">
      <labels>
        <label description="NO" languagecode="1033" />
      </labels>
      <Descriptions>
        <Description description="" languagecode="1033" />
      </Descriptions>
    </option>
    <option value="10" ExternalValue="" IsHidden="0">
      <labels>
        <label description="PL" languagecode="1033" />
      </labels>
      <Descriptions>
        <Description description="" languagecode="1033" />
      </Descriptions>
    </option>
    <option value="11" ExternalValue="" IsHidden="0">
      <labels>
        <label description="PT" languagecode="1033" />
      </labels>
      <Descriptions>
        <Description description="" languagecode="1033" />
      </Descriptions>
    </option>
    <option value="12" ExternalValue="" IsHidden="0">
      <labels>
        <label description="RO" languagecode="1033" />
      </labels>
      <Descriptions>
        <Description description="" languagecode="1033" />
      </Descriptions>
    </option>
    <option value="13" ExternalValue="" IsHidden="0">
      <labels>
        <label description="ES" languagecode="1033" />
      </labels>
      <Descriptions>
        <Description description="" languagecode="1033" />
      </Descriptions>
    </option>
    <option value="14" ExternalValue="" IsHidden="0">
      <labels>
        <label description="SV" languagecode="1033" />
      </labels>
      <Descriptions>
        <Description description="" languagecode="1033" />
      </Descriptions>
    </option>
    <option value="15" ExternalValue="" IsHidden="0">
      <labels>
        <label description="VI" languagecode="1033" />
      </labels>
      <Descriptions>
        <Description description="" languagecode="1033" />
      </Descriptions>
    </option>
  </options>
</optionset>